cleese/__init__.py
cleese/__main__.py
cleese/clients.py
cleese/commands.py
cleese/config.py
cleese/main.py
cleese/utils.py
cleese_mpd-0.16.2.dist-info/entry_points.txt
cleese_mpd-0.16.2.dist-info/WHEEL
cleese_mpd-0.16.2.dist-info/METADATA
cleese_mpd-0.16.2.dist-info/RECORD
