Metadata-Version: 2.1
Name: cleese-mpd
Version: 0.16.2
Summary: An MPD client based on ampdup.
License: MIT
Author: Tarcisio Eduardo Moreira Crocomo
Author-email: tarcisio.crocomo@gmail.com
Requires-Python: >=3.7,<4.0
Classifier: License :: OSI Approved :: MIT License
Classifier: Programming Language :: Python :: 3
Classifier: Programming Language :: Python :: 3.7
Classifier: Programming Language :: Python :: 3.8
Classifier: Programming Language :: Python :: 3.9
Requires-Dist: ampdup (>=0.12.0,<0.13.0)
Requires-Dist: carl (>=0.0.7,<0.0.8)
